mandl/__init__.py
mandl/mandl.py
mandl/prometheus.yml.template
mandl-0.1.4.dist-info/METADATA
mandl-0.1.4.dist-info/WHEEL
mandl-0.1.4.dist-info/RECORD
