Metadata-Version: 2.1
Name: mandl
Version: 0.1.4
Summary: A Python library for machine learning logging and observability. Extremely pre-alpha, don't use this.
Author: Eric Leijonmarck
Author-email: eric.leijonmarck@gmail.com
Requires-Python: >=3.8,<4.0
Classifier: Programming Language :: Python :: 3
Classifier: Programming Language :: Python :: 3.8
Classifier: Programming Language :: Python :: 3.9
Classifier: Programming Language :: Python :: 3.10
Classifier: Programming Language :: Python :: 3.11
Classifier: Programming Language :: Python :: 3.12
Requires-Dist: prometheus-client (>=0.19.0,<0.20.0)
Requires-Dist: psutil (>=5.9.6,<6.0.0)
Requires-Dist: python-dotenv (>=1.0.0,<2.0.0)
Requires-Dist: python-logging-loki (>=0.3.1,<0.4.0)
